hipulse/__init__.py
hipulse-0.1.0.dist-info/METADATA
hipulse-0.1.0.dist-info/WHEEL
hipulse-0.1.0.dist-info/top_level.txt
hipulse-0.1.0.dist-info/RECORD
